MANIFEST.in
setup.py
hal_codec/__init__.py
hal_codec.egg-info/PKG-INFO
hal_codec.egg-info/SOURCES.txt
hal_codec.egg-info/dependency_links.txt
hal_codec.egg-info/entry_points.txt
hal_codec.egg-info/requires.txt
hal_codec.egg-info/top_level.txt